[{"text": "Sleeping is the besstttttt.", "start": 0.089, "duration": 2.981}, {"text": "Waking up is the WOOORRRRSTTTT.", "start": 3.07, "duration": 1.27}, {"text": "JUST FIVE MORE MINUTESSSSS, Mom.", "start": 4.34, "duration": 1.66}, {"text": "Which never helps, does it?", "start": 6.0, "duration": 5.769}, {"text": "I had a roommate in college who's alarm went\noff at 7:15 for his 8am class.", "start": 11.769, "duration": 10.191}, {"text": "The radio, as loud as the volume would go.", "start": 21.96, "duration": 2.33}, {"text": "He didn't even flinch (or wake up), but I\nalmost hit the ceiling it scared me so much.", "start": 24.29, "duration": 4.64}, {"text": "We've done a lot of videos on sleep we even\nhave a sleep playlist but WAKING UP\u2026", "start": 28.93, "duration": 5.58}, {"text": "Some days, I just DON'T WANNA GET UP.", "start": 34.51, "duration": 1.979}, {"text": "Social jetlag, or the idea we HAVE to wake\nup before our natural rhythms WANT us to wake", "start": 36.489, "duration": 4.411}, {"text": "up affects 70 percent of the population according\nto a study in Current Biology.", "start": 40.9, "duration": 4.58}, {"text": "And difficulty waking up is called sleep inertia.", "start": 45.48, "duration": 2.84}, {"text": "A 2013 study in PlosOne describes it as, \"a\ntemporary period of reduced alertness and", "start": 48.32, "duration": 4.74}, {"text": "impaired performance.\"", "start": 53.06, "duration": 1.13}, {"text": "Scientific symptoms of sleep inertia are poor\nmemory and reaction time, inability to perform", "start": 54.19, "duration": 4.47}, {"text": "basic math and the suffering of alertness\nor attention.", "start": 58.66, "duration": 3.44}, {"text": "These symptoms can persist for an hour, and\nusually occurs when you wake up during slow-wave", "start": 62.1, "duration": 4.519}, {"text": "sleep.", "start": 66.619, "duration": 1.0}, {"text": "Sleep comes in order across four stages: Stage\nOne is the transition from wakefulness to", "start": 67.619, "duration": 5.261}, {"text": "a light sleep.", "start": 72.88, "duration": 1.0}, {"text": "During this 5 to 10 minute stage, the electrical\nsignals pulsing through your brain form theta", "start": 73.88, "duration": 5.089}, {"text": "waves.", "start": 78.969, "duration": 1.0}, {"text": "The next 20 minutes is Stage Two; the brain\nproduces rapid bursts of activity called sleep", "start": 79.969, "duration": 4.231}, {"text": "spindles, and then the heart rate slows and\nbody temperature dips.", "start": 84.2, "duration": 4.299}, {"text": "Stage Three is slow wave sleep or delta sleep.", "start": 88.499, "duration": 3.021}, {"text": "This lasts about an hour, and brain activity\ncomes in the form of delta waves.", "start": 91.52, "duration": 4.079}, {"text": "People here normally aren't responsive when\nyou call their name; and abnormal behaviors", "start": 95.599, "duration": 3.2}, {"text": "like bedwetting or sleepwalking are part of\nthe end of this Stage.", "start": 98.799, "duration": 4.731}, {"text": "Stage Four is the famous REM sleep, when dreams\nhappen!", "start": 103.53, "duration": 3.649}, {"text": "When you fall asleep you go through stage\none, and then back to Two.", "start": 107.179, "duration": 5.79}, {"text": "Then Two, Three, Four\u2026 back to Two.", "start": 112.969, "duration": 1.81}, {"text": "You'll do this four or five times.", "start": 114.779, "duration": 2.351}, {"text": "If your alarm goes off when you're in stage\nthree, the deepest of sleep, then you'll be", "start": 117.13, "duration": 4.529}, {"text": "jolted awake.", "start": 121.659, "duration": 1.0}, {"text": "And you'll get the worst of sleep inertia!", "start": 122.659, "duration": 2.48}, {"text": "This is usually when people describe feeling\nlike they were \"hit by a truck.\"", "start": 125.139, "duration": 4.35}, {"text": "The hormones surging through your body keeping\nyou in deep sleep are still floating around,", "start": 129.489, "duration": 4.56}, {"text": "affecting your now AWAKE body.", "start": 134.049, "duration": 2.101}, {"text": "Sleep inertia is still being studied, it was\nonly named in the late 70s, so, say it with", "start": 136.15, "duration": 3.71}, {"text": "me now, MORE RESEARCH IS NEEDED!", "start": 139.86, "duration": 2.57}, {"text": "But what we DO know, is the best medicine\nis to get out of bed and turn on the lights,", "start": 142.43, "duration": 5.449}, {"text": "because the retina is DIRECTLY tied to the\nsuprachiasmatic nucleus (SCN).", "start": 147.879, "duration": 5.401}, {"text": "The SCN controls our sleep-wake cycle and\nthe release of melatonin, which is a hormone", "start": 153.28, "duration": 4.079}, {"text": "that triggers the sleeping part of that cycle.", "start": 157.359, "duration": 2.671}, {"text": "Your phone doesn't count though.", "start": 160.03, "duration": 3.739}, {"text": "It's true that at night the blue light from\nphone and tablet screens mess with the SCN's", "start": 163.769, "duration": 4.401}, {"text": "regulation of the sleep/wake cycle.", "start": 168.17, "duration": 1.909}, {"text": "(So don't use them before sleep), but a study\nin PlosOne found that increasing blue light", "start": 170.079, "duration": 5.791}, {"text": "doesn't increase brain alertness during sleep\ninertia, so grabbing your phone first thing", "start": 175.87, "duration": 4.41}, {"text": "won't save you.", "start": 180.28, "duration": 1.0}, {"text": "Also, the snooze button is NOT your friend.", "start": 181.28, "duration": 1.87}, {"text": "If you're jolted from slow-wave sleep and\nallow your brain to drop into sleep again,", "start": 183.15, "duration": 4.07}, {"text": "you'll start the whole cycle over; causing\nyou to feel even WORSE.", "start": 187.22, "duration": 4.26}, {"text": "And don't set alarms every half-hour either,\nyou're not gradually waking yourself up, you're", "start": 191.48, "duration": 4.17}, {"text": "interrupting and restarting your sleep over\nand over.", "start": 195.65, "duration": 2.809}, {"text": "I'm guilty of this, and so are many of you;\nbut it's the worst.", "start": 198.459, "duration": 4.971}, {"text": "Like EVERYTHING, having a healthy sleep/wake\ncycle requires effort -- like running a race,", "start": 203.43, "duration": 4.119}, {"text": "we have to train to be good at it.", "start": 207.549, "duration": 1.961}, {"text": "Waking up is no different.", "start": 209.51, "duration": 1.19}, {"text": "Set one alarm and make yourself wake up when\nit goes off.", "start": 210.7, "duration": 5.679}, {"text": "Take down the blackout curtains so you get\nsome daylight and your retinas will tell your", "start": 216.379, "duration": 4.28}, {"text": "SCN it's wakeup time.", "start": 220.659, "duration": 1.58}, {"text": "Wake up on the weekend too, so you don't throw\noff your sleep schedule!", "start": 222.239, "duration": 3.801}, {"text": "A morning routine is the best; and everyone\nis different, but luckily, wakefulness is", "start": 226.04, "duration": 5.039}, {"text": "easy to train.", "start": 231.079, "duration": 1.121}, {"text": "But only you can do it.", "start": 232.2, "duration": 1.0}, {"text": "I used to be a night owl, but having to be\nup to make DNews for you every morning completely", "start": 233.2, "duration": 8.579}, {"text": "changed me.", "start": 241.779, "duration": 1.031}, {"text": "And\u2026 you know what?", "start": 242.81, "duration": 2.34}, {"text": "I kind of love it.", "start": 245.15, "duration": 8.14}]