[{"text": "[sighs]", "start": 0.083, "duration": 1.293}, {"text": "You know what we should all do?", "start": 4.671, "duration": 1.668}, {"text": "Go see a musical.", "start": 7.215, "duration": 1.585}, {"text": "Sure.", "start": 11.928, "duration": 1.085}, {"text": "You know which one\nwe should see?", "start": 14.597, "duration": 1.419}, {"text": "The 1996 Tony Award winner.", "start": 17.35, "duration": 3.212}, {"text": "Do you happen to know\nthe name of that one?", "start": 22.063, "duration": 2.336}, {"text": "I don't know, um, \"Grease?\"", "start": 24.399, "duration": 2.002}, {"text": "No.", "start": 28.236, "duration": 1.168}, {"text": "\"Rent?\"", "start": 31.781, "duration": 1.794}, {"text": "Yes! \"Rent!\"", "start": 33.575, "duration": 1.334}, {"text": "Okay, so when do you want to go?", "start": 36.286, "duration": 1.46}, {"text": "What? Oh, I'm sorry.\nI can't, I'm busy.", "start": 37.829, "duration": 2.836}, {"text": "- Hey.\n- 'Hey.'", "start": 43.835, "duration": 1.752}, {"text": "Man, it is so hard\nto shop for girls.", "start": 45.837, "duration": 3.42}, {"text": "Oh!", "start": 49.257, "duration": 1.084}, {"text": "Yes, it is, at Office Max!", "start": 50.425, "duration": 2.544}, {"text": "What did you get her?", "start": 55.638, "duration": 1.168}, {"text": "A pen.", "start": 58.641, "duration": 2.128}, {"text": "It's two gifts in one.\nIt's a pen that's also a clock.", "start": 61.102, "duration": 3.545}, {"text": "Huh?", "start": 64.647, "duration": 1.419}, {"text": "[laughs]", "start": 66.274, "duration": 1.001}, {"text": "You can't give her that.", "start": 67.442, "duration": 1.71}, {"text": "- Why not?\n- Because she's not 11!", "start": 69.152, "duration": 1.877}, {"text": "And it's not the seventh night\nof Chanukah!", "start": 72.614, "duration": 2.21}, {"text": "Okay, honey,\nwhat he means by that is..", "start": 77.952, "duration": 2.211}, {"text": "Well, this is a very nice gift", "start": 80.246, "duration": 1.752}, {"text": "maybe it's just not something\na boyfriend gives.", "start": 82.082, "duration": 2.711}, {"text": "Sure it is.", "start": 84.793, "duration": 1.418}, {"text": "She needs a pen for work.", "start": 86.461, "duration": 1.501}, {"text": "She's writing,\nshe turns it over.", "start": 87.962, "duration": 1.752}, {"text": "Whoa! It's time\nfor my date with Joey!", "start": 89.714, "duration": 2.336}, {"text": "Alright, look, look. What..", "start": 94.636, "duration": 1.835}, {"text": "What did you get\nfor Angela Del Veccio", "start": 96.471, "duration": 1.543}, {"text": "for her birthday?", "start": 98.014, "duration": 1.418}, {"text": "She didn't have a birthday\nwhile we were going out.", "start": 99.516, "duration": 2.002}, {"text": "For three years?", "start": 101.601, "duration": 1.335}, {"text": "Look, it's too late,\nand I got an audition.", "start": 105.939, "duration": 3.044}, {"text": "I can't shop anymore. I..", "start": 108.983, "duration": 2.878}, {"text": "Alright, I will go out", "start": 111.945, "duration": 1.835}, {"text": "and I will try\nto find something for her, okay?", "start": 113.78, "duration": 2.836}, {"text": "Thanks, man.", "start": 116.616, "duration": 1.627}, {"text": "And oh, while you're at it", "start": 118.243, "duration": 1.376}, {"text": "could you get her a card?", "start": 119.619, "duration": 2.211}, {"text": "Would you like me to write her\na little poem as well?", "start": 121.871, "duration": 3.045}, {"text": "Or just get a card\nthat has a poem already in it.", "start": 125.166, "duration": 3.128}]