[{"text": "I\u2019ve been tracing dirty money for more than\n30 years.", "start": 0.39, "duration": 3.13}, {"text": "Studying kleptocrats all over the world, distinct\npatterns emerge.", "start": 3.52, "duration": 4.34}, {"text": "The thing about kleptocrats is that the moves\nand tricks they like to use each contain the", "start": 12.82, "duration": 5.25}, {"text": "seeds of their own destruction.", "start": 18.07, "duration": 1.859}, {"text": "They can get caught at every stage.", "start": 19.929, "duration": 2.451}, {"text": "And those patterns are the basis of our new\ngame, Kleptocrat: How to Hide Dirty Money.", "start": 22.38, "duration": 5.69}, {"text": "In virtually every case, corrupt people took\nsix separate steps to conceal their assets:", "start": 28.07, "duration": 7.46}, {"text": "Take the money under the table;\nCreate a financial structure to hide it;", "start": 35.53, "duration": 4.239}, {"text": "Move the money into the structure;\nNetwork with family members to run the operation;", "start": 39.769, "duration": 5.531}, {"text": "Cover up their tracks;\nAnd last, since it\u2019s no fun for the money", "start": 45.3, "duration": 3.32}, {"text": "to sit gathering dust, take the money out and\nenjoy it.", "start": 48.62, "duration": 3.93}, {"text": "I know nothing about Paul Manafort or the\nallegations in the indictment against him.", "start": 52.55, "duration": 4.79}, {"text": "I read the Manafort indictment, and lo and\nbehold, the allegations match the six-step", "start": 57.34, "duration": 4.449}, {"text": "pattern.", "start": 61.789, "duration": 1.0}, {"text": "It says Manafort allegedly took $18 million\nsecretly from Ukraine.", "start": 62.789, "duration": 4.58}, {"text": "That\u2019s step 1.", "start": 67.369, "duration": 1.921}, {"text": "Step 2: Manafort allegedly created a blizzard\nof offshore companies, with names like Bletilla.", "start": 69.29, "duration": 6.35}, {"text": "They\u2019re on tiny islands I bet most people\ncouldn\u2019t even find on map.", "start": 75.64, "duration": 4.049}, {"text": "Then step 3: He allegedly started moving the\nmoney around.", "start": 79.689, "duration": 4.521}, {"text": "Six separate companies on the island of Cyprus\nsent more than $5 million to a home-improvement", "start": 84.21, "duration": 6.259}, {"text": "firm in the Hamptons.", "start": 90.469, "duration": 2.22}, {"text": "Step 4: Manafort allegedly enlisted some of\nhis relatives to help.", "start": 92.689, "duration": 4.46}, {"text": "The indictment says he got his daughter and\nson-in-law to pretend to live in the", "start": 97.149, "duration": 4.04}, {"text": "real estate he was buying.", "start": 101.189, "duration": 1.131}, {"text": "Step 5 is covering up your secret money.", "start": 102.32, "duration": 2.96}, {"text": "Manafort allegedly lied to his accountants,\nand to federal agents, about the funds.", "start": 105.28, "duration": 5.729}, {"text": "He used multiple passports.", "start": 111.009, "duration": 1.36}, {"text": "And he \u201cdeveloped a false and misleading\ncover story.\u201d", "start": 112.369, "duration": 4.17}, {"text": "Lastly, Manafort allegedly brought the money\nout to play.", "start": 116.539, "duration": 4.921}, {"text": "The indictment says he \u201cused his hidden\noverseas wealth to enjoy a lavish lifestyle", "start": 121.46, "duration": 6.14}, {"text": "in the United States.\u201d", "start": 127.6, "duration": 1.37}, {"text": "I guess sometimes a game can help you understand\nthe news.", "start": 128.97, "duration": 3.29}]