[{"text": "As we sail down the river of Slurm, you'll see our mixologists at work.", "start": 0.15, "duration": 4.43}, {"text": "They take 900 of the finest ingredients, add a touch of", "start": 4.81, "duration": 4.299}, {"text": "childlike delights, and mix it all with glacial spring water from our", "start": 9.179, "duration": 4.921}, {"text": "glacial spring water generator.", "start": 14.1, "duration": 1.92}, {"text": "Then, last of all,", "start": 18.823, "duration": 1.597}, {"text": "we add the secret ingredient that makes Slurm so deliciously addictive.", "start": 20.71, "duration": 4.75}, {"text": "So, what's the secret ingredient?", "start": 28.151, "duration": 1.428}, {"text": "It's whatever your imagination wants it to be!", "start": 29.743, "duration": 2.289}, {"text": "Oh. Well, what is it really?", "start": 32.15, "duration": 1.531}, {"text": "That's not for you to know.", "start": 33.97, "duration": 1.906}, {"text": "Now over here, the Grunka Lunkas are inducing Wumpus berries to", "start": 36.666, "duration": 3.708}, {"text": "release their flavor, using sensual massage.", "start": 40.432, "duration": 3.395}, {"text": "Psst.", "start": 44.702, "duration": 0.461}, {"text": "Those berries, those are the secret ingredient, right?", "start": 45.54, "duration": 2.603}, {"text": "No.", "start": 48.37, "duration": 0.477}, {"text": "Are you positive?", "start": 48.886, "duration": 0.789}, {"text": "Yes.", "start": 49.699, "duration": 0.797}, {"text": "I'm just asking 'cause they look kinda secret.", "start": 50.52, "duration": 2.061}, {"text": "Enough!", "start": 52.605, "duration": 0.591}, {"text": "There will be no further questions.", "start": 53.565, "duration": 1.703}, {"text": "Why?", "start": 55.573, "duration": 0.57}, {"text": "Hey, look. The disgusting little men are starting to sing.", "start": 56.362, "duration": 3.338}, {"text": "\u266b Grunka Lunka dunkety-doo,", "start": 62.919, "duration": 2.554}, {"text": "we've got a friendly warning for you.", "start": 65.824, "duration": 2.622}, {"text": "Grunka Lunka dunkety-dasis,", "start": 68.711, "duration": 2.595}, {"text": "the secret of Slurm's on a need-to-know basis.", "start": 71.33, "duration": 2.991}, {"text": "Asking questions in school is a great way to learn.", "start": 75.61, "duration": 3.008}, {"text": "If you try that stuff here you might get your legs broke.", "start": 78.642, "duration": 2.892}, {"text": "We once found a dead guy face down in the Slurm.", "start": 81.558, "duration": 2.968}, {"text": "It could easily happen again to you folks.", "start": 84.55, "duration": 2.765}, {"text": "So, keep your head down and keep your mouth shut.", "start": 87.339, "duration": 2.758}, {"text": "Grunka Lunka, Lunka dunkety-dutt! \u266b", "start": 90.386, "duration": 3.058}, {"text": "Hey, I don't pay you to sing.", "start": 93.68, "duration": 2.296}, {"text": "You just used up today's bathroom break.", "start": 96.062, "duration": 2.0}, {"text": "Hard ass.", "start": 98.648, "duration": 0.562}, {"text": "I heard that.", "start": 99.312, "duration": 1.577}, {"text": "Now on your right, you'll see the Slurm Master checking", "start": 102.085, "duration": 3.351}, {"text": "the Slurm for color and bouquet.", "start": 105.46, "duration": 2.156}, {"text": "So thirsty.", "start": 109.06, "duration": 1.325}, {"text": "Then, he tastes it. He tastes it and tastes it.", "start": 110.666, "duration": 3.187}, {"text": "Then tastes it some more.", "start": 114.056, "duration": 1.344}, {"text": "Uh, could I have some Slurm please?", "start": 115.947, "duration": 1.818}, {"text": "No food or drink allowed on the tour.", "start": 117.79, "duration": 2.063}, {"text": "You'll have to wait till you're", "start": 120.017, "duration": 1.122}, {"text": "partying with Slurms MacKenzie.", "start": 121.163, "duration": 2.057}, {"text": "When will that be?", "start": 123.335, "duration": 0.929}, {"text": "Soon enough.", "start": 124.444, "duration": 0.805}, {"text": "Thats not soon enough.", "start": 125.491, "duration": 1.18}, {"text": "Hey, what's behind that door?", "start": 127.0, "duration": 1.42}, {"text": "Nothing.", "start": 129.061, "duration": 0.682}, {"text": "Is it the secret ingredient?", "start": 129.99, "duration": 1.23}, {"text": "\u266b Grunka Lunka dunkety-dingredient.", "start": 131.53, "duration": 2.538}, {"text": "You should not ask about the secret ingredient! \u266b", "start": 134.092, "duration": 2.795}, {"text": "Okay, okay.", "start": 136.912, "duration": 0.818}, {"text": "We get the point.", "start": 137.755, "duration": 1.336}, {"text": "I was just curious because of the armed guards.", "start": 139.435, "duration": 2.353}, {"text": "\u266b Grunka Lunka dunkety-darmedguards ... \u266b", "start": 141.867, "duration": 2.718}, {"text": "Shut the hell up!", "start": 144.632, "duration": 1.159}, {"text": "So, you're telling me I could fire my whole staff", "start": 150.451, "duration": 2.14}, {"text": "and hire Grunka Lunkas at half the cost?", "start": 152.615, "duration": 1.906}, {"text": "That's right. They think they have a good union but they don't.", "start": 154.779, "duration": 3.086}, {"text": "They're basically slaves.", "start": 158.161, "duration": 1.579}, {"text": "What are you doing?", "start": 166.13, "duration": 1.17}, {"text": "I'm dying of thirst.", "start": 167.6, "duration": 1.187}, {"text": "Grab my feet and dunk my head in so I can drink.", "start": 168.811, "duration": 2.179}, {"text": "No. That's moronic.", "start": 171.23, "duration": 1.07}, {"text": "Fine. I'll let go and swim around in the Slurm", "start": 172.45, "duration": 2.341}, {"text": "and drink as much as I want.", "start": 174.816, "duration": 1.085}, {"text": "Help! I can't swim!", "start": 177.916, "duration": 1.127}, {"text": "Bender, why did you jump in?", "start": 193.979, "duration": 1.563}, {"text": "Everybody was doing it. I just wanted to be popular.", "start": 195.659, "duration": 2.741}]