[{"text": "So, I'll start with this: a couple\nyears ago, an event planner called me", "start": 16.86, "duration": 3.461}, {"text": "because I was going\nto do a speaking event.", "start": 20.345, "duration": 2.049}, {"text": "And she called, and she said,", "start": 22.418, "duration": 1.69}, {"text": "\"I'm really struggling with how\nto write about you on the little flyer.\"", "start": 24.132, "duration": 3.572}, {"text": "And I thought,\n\"Well, what's the struggle?\"", "start": 27.728, "duration": 2.048}, {"text": "And she said, \"Well, I saw you speak,", "start": 30.488, "duration": 1.904}, {"text": "and I'm going to call you\na researcher, I think,", "start": 32.416, "duration": 2.485}, {"text": "but I'm afraid if I call you\na researcher, no one will come,", "start": 34.925, "duration": 2.888}, {"text": "because they'll think\nyou're boring and irrelevant.\"", "start": 37.837, "duration": 2.459}, {"text": "(Laughter)", "start": 40.32, "duration": 1.001}, {"text": "And I was like, \"Okay.\"", "start": 41.345, "duration": 1.576}, {"text": "And she said, \"But the thing\nI liked about your talk", "start": 42.945, "duration": 2.478}, {"text": "is you're a storyteller.", "start": 45.447, "duration": 1.216}, {"text": "So I think what I'll do\nis just call you a storyteller.\"", "start": 46.687, "duration": 2.714}, {"text": "And of course, the academic,\ninsecure part of me", "start": 49.99, "duration": 2.976}, {"text": "was like, \"You're going\nto call me a what?\"", "start": 52.99, "duration": 2.31}, {"text": "And she said, \"I'm going\nto call you a storyteller.\"", "start": 55.324, "duration": 2.548}, {"text": "And I was like, \"Why not 'magic pixie'?\"", "start": 57.896, "duration": 2.849}, {"text": "(Laughter)", "start": 60.769, "duration": 2.479}, {"text": "I was like, \"Let me think\nabout this for a second.\"", "start": 63.648, "duration": 3.278}, {"text": "I tried to call deep on my courage.", "start": 67.291, "duration": 2.539}, {"text": "And I thought, you know,\nI am a storyteller.", "start": 69.854, "duration": 3.112}, {"text": "I'm a qualitative researcher.", "start": 72.99, "duration": 1.404}, {"text": "I collect stories; that's what I do.", "start": 74.418, "duration": 1.721}, {"text": "And maybe stories\nare just data with a soul.", "start": 76.656, "duration": 2.905}, {"text": "And maybe I'm just a storyteller.", "start": 79.585, "duration": 2.381}, {"text": "And so I said, \"You know what?", "start": 81.99, "duration": 1.659}, {"text": "Why don't you just say\nI'm a researcher-storyteller.\"", "start": 83.673, "duration": 2.641}, {"text": "And she went, \"Ha ha.\nThere's no such thing.\"", "start": 86.338, "duration": 3.628}, {"text": "(Laughter)", "start": 89.99, "duration": 1.683}, {"text": "So I'm a researcher-storyteller,\nand I'm going to talk to you today --", "start": 91.697, "duration": 3.977}, {"text": "we're talking about\nexpanding perception --", "start": 95.698, "duration": 2.049}, {"text": "and so I want to talk to you\nand tell some stories", "start": 97.771, "duration": 2.382}, {"text": "about a piece of my research\nthat fundamentally expanded my perception", "start": 100.177, "duration": 5.159}, {"text": "and really actually changed\nthe way that I live and love", "start": 105.36, "duration": 2.889}, {"text": "and work and parent.", "start": 108.273, "duration": 1.174}, {"text": "And this is where my story starts.", "start": 110.093, "duration": 2.132}, {"text": "When I was a young researcher,\ndoctoral student,", "start": 112.99, "duration": 2.683}, {"text": "my first year, I had\na research professor who said to us,", "start": 115.697, "duration": 3.977}, {"text": "\"Here's the thing, if you cannot\nmeasure it, it does not exist.\"", "start": 119.698, "duration": 3.946}, {"text": "And I thought he was just\nsweet-talking me.", "start": 125.374, "duration": 2.592}, {"text": "I was like, \"Really?\"\nand he was like, \"Absolutely.\"", "start": 128.339, "duration": 2.437}, {"text": "And so you have to understand", "start": 130.8, "duration": 2.253}, {"text": "that I have a bachelor's\nand a master's in social work,", "start": 133.077, "duration": 2.58}, {"text": "and I was getting my Ph.D. in social work,\nso my entire academic career", "start": 135.681, "duration": 3.374}, {"text": "was surrounded by people who kind of\nbelieved in the \"life's messy, love it.\"", "start": 139.079, "duration": 5.617}, {"text": "And I'm more of the, \"life's messy,\nclean it up, organize it", "start": 145.474, "duration": 5.428}, {"text": "and put it into a bento box.\"", "start": 150.926, "duration": 1.777}, {"text": "(Laughter)", "start": 152.727, "duration": 1.976}, {"text": "And so to think that I had found my way,\nto found a career that takes me --", "start": 155.02, "duration": 5.311}, {"text": "really, one of the big sayings\nin social work is,", "start": 160.355, "duration": 3.333}, {"text": "\"Lean into the discomfort of the work.\"", "start": 163.712, "duration": 2.095}, {"text": "And I'm like, knock discomfort\nupside the head", "start": 166.537, "duration": 2.532}, {"text": "and move it over and get all A's.", "start": 169.093, "duration": 2.278}, {"text": "That was my mantra.", "start": 171.395, "duration": 1.912}, {"text": "So I was very excited about this.", "start": 174.99, "duration": 1.976}, {"text": "And so I thought, you know what,\nthis is the career for me,", "start": 176.99, "duration": 2.976}, {"text": "because I am interested\nin some messy topics.", "start": 179.99, "duration": 2.976}, {"text": "But I want to be able\nto make them not messy.", "start": 182.99, "duration": 2.371}, {"text": "I want to understand them.", "start": 185.385, "duration": 1.322}, {"text": "I want to hack into these things\nthat I know are important", "start": 186.731, "duration": 3.577}, {"text": "and lay the code out for everyone to see.", "start": 190.332, "duration": 1.976}, {"text": "So where I started was with connection.", "start": 192.99, "duration": 2.659}, {"text": "Because, by the time\nyou're a social worker for 10 years,", "start": 195.673, "duration": 3.412}, {"text": "what you realize is that connection\nis why we're here.", "start": 199.109, "duration": 4.707}, {"text": "It's what gives purpose\nand meaning to our lives.", "start": 203.84, "duration": 2.38}, {"text": "This is what it's all about.", "start": 207.076, "duration": 1.786}, {"text": "It doesn't matter whether\nyou talk to people", "start": 208.886, "duration": 2.097}, {"text": "who work in social justice,\nmental health and abuse and neglect,", "start": 211.007, "duration": 3.092}, {"text": "what we know is that connection,\nthe ability to feel connected, is --", "start": 214.123, "duration": 5.341}, {"text": "neurobiologically\nthat's how we're wired --", "start": 219.948, "duration": 2.018}, {"text": "it's why we're here.", "start": 221.99, "duration": 1.379}, {"text": "So I thought, you know what,\nI'm going to start with connection.", "start": 223.393, "duration": 3.013}, {"text": "Well, you know that situation", "start": 227.067, "duration": 1.897}, {"text": "where you get an evaluation\nfrom your boss,", "start": 228.988, "duration": 2.508}, {"text": "and she tells you 37 things\nthat you do really awesome,", "start": 231.52, "duration": 2.786}, {"text": "and one \"opportunity for growth?\"", "start": 234.33, "duration": 2.374}, {"text": "(Laughter)", "start": 236.728, "duration": 1.809}, {"text": "And all you can think about\nis that opportunity for growth, right?", "start": 239.196, "duration": 3.468}, {"text": "Well, apparently this is the way\nmy work went as well,", "start": 242.688, "duration": 2.698}, {"text": "because, when you ask people about love,\nthey tell you about heartbreak.", "start": 245.41, "duration": 4.977}, {"text": "When you ask people about belonging,", "start": 250.411, "duration": 2.634}, {"text": "they'll tell you their most excruciating\nexperiences of being excluded.", "start": 253.069, "duration": 3.952}, {"text": "And when you ask people about connection,", "start": 257.045, "duration": 2.501}, {"text": "the stories they told me\nwere about disconnection.", "start": 259.57, "duration": 2.538}, {"text": "So very quickly -- really about six weeks\ninto this research --", "start": 263.118, "duration": 3.025}, {"text": "I ran into this unnamed thing\nthat absolutely unraveled connection", "start": 266.167, "duration": 6.022}, {"text": "in a way that I didn't understand\nor had never seen.", "start": 272.213, "duration": 2.46}, {"text": "And so I pulled back out of the research", "start": 275.109, "duration": 1.977}, {"text": "and thought, I need\nto figure out what this is.", "start": 277.11, "duration": 2.23}, {"text": "And it turned out to be shame.", "start": 279.364, "duration": 2.179}, {"text": "And shame is really easily understood\nas the fear of disconnection:", "start": 283.212, "duration": 3.278}, {"text": "Is there something about me that,\nif other people know it or see it,", "start": 287.213, "duration": 4.556}, {"text": "that I won't be worthy of connection?", "start": 291.793, "duration": 3.166}, {"text": "The things I can tell you about it:", "start": 295.593, "duration": 1.682}, {"text": "It's universal; we all have it.", "start": 297.299, "duration": 1.667}, {"text": "The only people who don't experience shame", "start": 298.99, "duration": 2.0}, {"text": "have no capacity for human\nempathy or connection.", "start": 301.014, "duration": 2.334}, {"text": "No one wants to talk about it,", "start": 303.372, "duration": 1.594}, {"text": "and the less you talk about it,\nthe more you have it.", "start": 304.99, "duration": 2.571}, {"text": "What underpinned this shame,\nthis \"I'm not good enough,\" --", "start": 309.005, "duration": 5.166}, {"text": "which, we all know that feeling:", "start": 314.195, "duration": 1.604}, {"text": "\"I'm not blank enough.\nI'm not thin enough,", "start": 315.823, "duration": 2.049}, {"text": "rich enough, beautiful enough,\nsmart enough, promoted enough.\"", "start": 317.896, "duration": 3.254}, {"text": "The thing that underpinned this\nwas excruciating vulnerability.", "start": 321.174, "duration": 4.976}, {"text": "This idea of, in order\nfor connection to happen,", "start": 326.862, "duration": 4.104}, {"text": "we have to allow ourselves\nto be seen, really seen.", "start": 330.99, "duration": 3.746}, {"text": "And you know how I feel\nabout vulnerability. I hate vulnerability.", "start": 336.061, "duration": 3.198}, {"text": "And so I thought, this is my chance\nto beat it back with my measuring stick.", "start": 339.283, "duration": 4.498}, {"text": "I'm going in, I'm going\nto figure this stuff out,", "start": 343.805, "duration": 2.691}, {"text": "I'm going to spend a year,\nI'm going to totally deconstruct shame,", "start": 346.52, "duration": 3.31}, {"text": "I'm going to understand\nhow vulnerability works,", "start": 349.854, "duration": 2.278}, {"text": "and I'm going to outsmart it.", "start": 352.156, "duration": 1.435}, {"text": "So I was ready, and I was really excited.", "start": 354.64, "duration": 2.27}, {"text": "As you know,\nit's not going to turn out well.", "start": 360.239, "duration": 2.143}, {"text": "(Laughter)", "start": 362.406, "duration": 2.513}, {"text": "You know this.", "start": 364.943, "duration": 1.594}, {"text": "So, I could tell you a lot about shame,", "start": 366.561, "duration": 1.889}, {"text": "but I'd have to borrow\neveryone else's time.", "start": 368.474, "duration": 2.097}, {"text": "But here's what I can tell you\nthat it boils down to --", "start": 370.595, "duration": 2.857}, {"text": "and this may be one of the most important\nthings that I've ever learned", "start": 373.476, "duration": 3.382}, {"text": "in the decade of doing this research.", "start": 376.882, "duration": 1.864}, {"text": "My one year turned into six years:", "start": 380.068, "duration": 4.192}, {"text": "Thousands of stories, hundreds\nof long interviews, focus groups.", "start": 384.284, "duration": 4.682}, {"text": "At one point, people were\nsending me journal pages", "start": 388.99, "duration": 2.381}, {"text": "and sending me their stories --", "start": 391.395, "duration": 1.837}, {"text": "thousands of pieces of data in six years.", "start": 393.256, "duration": 3.992}, {"text": "And I kind of got a handle on it.", "start": 397.272, "duration": 1.694}, {"text": "I kind of understood, this is\nwhat shame is, this is how it works.", "start": 398.99, "duration": 3.099}, {"text": "I wrote a book, I published a theory,\nbut something was not okay --", "start": 403.452, "duration": 6.247}, {"text": "and what it was is that, if I roughly\ntook the people I interviewed", "start": 409.723, "duration": 4.156}, {"text": "and divided them into people who really\nhave a sense of worthiness --", "start": 413.903, "duration": 6.572}, {"text": "that's what this comes down to,\na sense of worthiness --", "start": 420.499, "duration": 2.762}, {"text": "they have a strong sense\nof love and belonging --", "start": 423.285, "duration": 3.222}, {"text": "and folks who struggle for it,", "start": 426.531, "duration": 1.651}, {"text": "and folks who are always wondering\nif they're good enough.", "start": 428.206, "duration": 3.1}, {"text": "There was only one variable that separated", "start": 431.33, "duration": 2.239}, {"text": "the people who have a strong sense\nof love and belonging", "start": 433.593, "duration": 2.74}, {"text": "and the people who really struggle for it.", "start": 436.357, "duration": 2.259}, {"text": "And that was, the people who have\na strong sense of love and belonging", "start": 438.64, "duration": 3.718}, {"text": "believe they're worthy\nof love and belonging.", "start": 442.382, "duration": 2.404}, {"text": "That's it.", "start": 445.704, "duration": 1.15}, {"text": "They believe they're worthy.", "start": 447.505, "duration": 1.488}, {"text": "And to me, the hard part of the one thing\nthat keeps us out of connection", "start": 450.736, "duration": 5.818}, {"text": "is our fear that we're not\nworthy of connection,", "start": 456.578, "duration": 3.215}, {"text": "was something that,\npersonally and professionally,", "start": 459.817, "duration": 2.403}, {"text": "I felt like I needed to understand better.", "start": 462.244, "duration": 2.222}, {"text": "So what I did is I took\nall of the interviews", "start": 464.807, "duration": 4.977}, {"text": "where I saw worthiness,\nwhere I saw people living that way,", "start": 469.808, "duration": 2.818}, {"text": "and just looked at those.", "start": 472.65, "duration": 1.888}, {"text": "What do these people have in common?", "start": 475.314, "duration": 2.048}, {"text": "I have a slight office supply addiction,\nbut that's another talk.", "start": 477.386, "duration": 4.643}, {"text": "So I had a manila folder,\nand I had a Sharpie,", "start": 482.053, "duration": 3.477}, {"text": "and I was like, what am I going\nto call this research?", "start": 485.554, "duration": 2.62}, {"text": "And the first words that came\nto my mind were \"whole-hearted.\"", "start": 488.198, "duration": 2.99}, {"text": "These are whole-hearted people,\nliving from this deep sense of worthiness.", "start": 491.807, "duration": 3.516}, {"text": "So I wrote at the top\nof the manila folder,", "start": 495.347, "duration": 2.856}, {"text": "and I started looking at the data.", "start": 498.227, "duration": 1.929}, {"text": "In fact, I did it first in a four-day,\nvery intensive data analysis,", "start": 500.18, "duration": 5.993}, {"text": "where I went back, pulled the interviews,\nthe stories, pulled the incidents.", "start": 506.197, "duration": 3.577}, {"text": "What's the theme? What's the pattern?", "start": 509.798, "duration": 1.779}, {"text": "My husband left town with the kids", "start": 512.37, "duration": 2.977}, {"text": "because I always go into this\nJackson Pollock crazy thing,", "start": 515.371, "duration": 2.977}, {"text": "where I'm just writing\nand in my researcher mode.", "start": 518.372, "duration": 3.745}, {"text": "And so here's what I found.", "start": 523.625, "duration": 1.547}, {"text": "What they had in common\nwas a sense of courage.", "start": 528.114, "duration": 2.852}, {"text": "And I want to separate courage\nand bravery for you for a minute.", "start": 531.624, "duration": 3.097}, {"text": "Courage, the original\ndefinition of courage,", "start": 534.745, "duration": 2.441}, {"text": "when it first came\ninto the English language --", "start": 537.21, "duration": 2.239}, {"text": "it's from the Latin word \"cor,\"\nmeaning \"heart\" --", "start": 539.473, "duration": 2.353}, {"text": "and the original definition was to tell\nthe story of who you are", "start": 541.85, "duration": 3.011}, {"text": "with your whole heart.", "start": 544.885, "duration": 1.414}, {"text": "And so these folks had, very simply,\nthe courage to be imperfect.", "start": 547.059, "duration": 4.174}, {"text": "They had the compassion to be kind\nto themselves first and then to others,", "start": 553.632, "duration": 4.977}, {"text": "because, as it turns out,", "start": 558.633, "duration": 1.199}, {"text": "we can't practice compassion\nwith other people", "start": 559.856, "duration": 2.234}, {"text": "if we can't treat ourselves kindly.", "start": 562.114, "duration": 1.743}, {"text": "And the last was they had connection,\nand -- this was the hard part --", "start": 564.259, "duration": 4.397}, {"text": "as a result of authenticity,", "start": 568.68, "duration": 2.977}, {"text": "they were willing to let go\nof who they thought they should be", "start": 571.681, "duration": 3.285}, {"text": "in order to be who they were,\nwhich you have to absolutely do that", "start": 574.99, "duration": 4.604}, {"text": "for connection.", "start": 579.618, "duration": 1.173}, {"text": "The other thing that they had\nin common was this:", "start": 583.323, "duration": 4.0}, {"text": "They fully embraced vulnerability.", "start": 590.91, "duration": 3.08}, {"text": "They believed that what made them\nvulnerable made them beautiful.", "start": 595.679, "duration": 6.651}, {"text": "They didn't talk about vulnerability\nbeing comfortable,", "start": 606.141, "duration": 3.825}, {"text": "nor did they really talk\nabout it being excruciating --", "start": 609.99, "duration": 2.826}, {"text": "as I had heard it earlier\nin the shame interviewing.", "start": 612.84, "duration": 2.478}, {"text": "They just talked about it being necessary.", "start": 615.342, "duration": 2.23}, {"text": "They talked about the willingness\nto say, \"I love you\" first ...", "start": 618.633, "duration": 3.976}, {"text": "the willingness to do something\nwhere there are no guarantees ...", "start": 624.378, "duration": 5.373}, {"text": "the willingness to breathe\nthrough waiting for the doctor to call", "start": 631.283, "duration": 4.335}, {"text": "after your mammogram.", "start": 635.642, "duration": 1.283}, {"text": "They're willing to invest\nin a relationship", "start": 638.631, "duration": 3.265}, {"text": "that may or may not work out.", "start": 641.92, "duration": 1.45}, {"text": "They thought this was fundamental.", "start": 644.465, "duration": 1.87}, {"text": "I personally thought it was betrayal.", "start": 647.442, "duration": 2.619}, {"text": "I could not believe I had pledged\nallegiance to research, where our job --", "start": 650.847, "duration": 4.596}, {"text": "you know, the definition of research\nis to control and predict,", "start": 655.467, "duration": 4.064}, {"text": "to study phenomena for the explicit\nreason to control and predict.", "start": 659.555, "duration": 4.643}, {"text": "And now my mission to control and predict", "start": 664.222, "duration": 4.366}, {"text": "had turned up the answer\nthat the way to live is with vulnerability", "start": 668.612, "duration": 3.569}, {"text": "and to stop controlling and predicting.", "start": 672.205, "duration": 2.098}, {"text": "This led to a little breakdown --", "start": 674.327, "duration": 1.777}, {"text": "(Laughter)", "start": 676.902, "duration": 5.064}, {"text": "-- which actually looked more like this.", "start": 681.99, "duration": 2.976}, {"text": "(Laughter)", "start": 684.99, "duration": 1.493}, {"text": "And it did.", "start": 686.507, "duration": 1.977}, {"text": "I call it a breakdown; my therapist\ncalls it a spiritual awakening.", "start": 688.508, "duration": 3.18}, {"text": "(Laughter)", "start": 691.712, "duration": 1.234}, {"text": "A spiritual awakening\nsounds better than breakdown,", "start": 692.97, "duration": 2.417}, {"text": "but I assure you, it was a breakdown.", "start": 695.411, "duration": 1.777}, {"text": "And I had to put my data away\nand go find a therapist.", "start": 697.212, "duration": 2.904}, {"text": "Let me tell you something:\nyou know who you are", "start": 700.14, "duration": 2.231}, {"text": "when you call your friends and say,\n\"I think I need to see somebody.", "start": 702.395, "duration": 3.24}, {"text": "Do you have any recommendations?\"", "start": 705.659, "duration": 1.806}, {"text": "Because about five\nof my friends were like,", "start": 707.489, "duration": 2.049}, {"text": "\"Wooo, I wouldn't want\nto be your therapist.\"", "start": 709.562, "duration": 2.144}, {"text": "(Laughter)", "start": 711.73, "duration": 2.738}, {"text": "I was like, \"What does that mean?\"", "start": 714.492, "duration": 1.977}, {"text": "And they're like,\n\"I'm just saying, you know.", "start": 716.493, "duration": 3.207}, {"text": "Don't bring your measuring stick.\"", "start": 719.724, "duration": 1.977}, {"text": "(Laughter)", "start": 721.725, "duration": 2.736}, {"text": "I was like, \"Okay.\"", "start": 724.485, "duration": 1.2}, {"text": "So I found a therapist.", "start": 726.545, "duration": 1.834}, {"text": "My first meeting with her, Diana --", "start": 728.403, "duration": 1.903}, {"text": "I brought in my list of the way\nthe whole-hearted live, and I sat down.", "start": 732.109, "duration": 4.294}, {"text": "And she said, \"How are you?\"", "start": 736.427, "duration": 1.809}, {"text": "And I said, \"I'm great. I'm okay.\"", "start": 738.26, "duration": 3.595}, {"text": "She said, \"What's going on?\"", "start": 741.879, "duration": 1.524}, {"text": "And this is a therapist\nwho sees therapists,", "start": 743.427, "duration": 2.619}, {"text": "because we have to go to those,\nbecause their B.S. meters are good.", "start": 746.07, "duration": 5.213}, {"text": "(Laughter)", "start": 751.307, "duration": 1.976}, {"text": "And so I said, \"Here's the thing,\nI'm struggling.\"", "start": 753.736, "duration": 3.833}, {"text": "And she said, \"What's the struggle?\"", "start": 757.593, "duration": 1.81}, {"text": "And I said, \"Well, I have\na vulnerability issue.", "start": 760.442, "duration": 2.261}, {"text": "And I know that vulnerability\nis the core of shame and fear", "start": 762.727, "duration": 5.355}, {"text": "and our struggle for worthiness,", "start": 768.106, "duration": 1.597}, {"text": "but it appears that it's also\nthe birthplace of joy, of creativity,", "start": 769.727, "duration": 5.676}, {"text": "of belonging, of love.", "start": 775.427, "duration": 1.976}, {"text": "And I think I have a problem,\nand I need some help.\"", "start": 777.776, "duration": 5.436}, {"text": "And I said, \"But here's the thing:\nno family stuff, no childhood shit.\"", "start": 783.236, "duration": 5.167}, {"text": "(Laughter)", "start": 788.427, "duration": 1.976}, {"text": "\"I just need some strategies.\"", "start": 790.427, "duration": 2.976}, {"text": "(Laughter)", "start": 793.427, "duration": 3.976}, {"text": "(Applause)", "start": 797.427, "duration": 3.585}, {"text": "Thank you.", "start": 801.036, "duration": 1.562}, {"text": "So she goes like this.", "start": 804.283, "duration": 1.477}, {"text": "(Laughter)", "start": 807.427, "duration": 2.356}, {"text": "And then I said, \"It's bad, right?\"", "start": 809.807, "duration": 2.596}, {"text": "And she said, \"It's neither good nor bad.\"", "start": 812.427, "duration": 2.976}, {"text": "(Laughter)", "start": 815.427, "duration": 1.833}, {"text": "\"It just is what it is.\"", "start": 817.284, "duration": 1.634}, {"text": "And I said, \"Oh my God,\nthis is going to suck.\"", "start": 819.664, "duration": 2.739}, {"text": "(Laughter)", "start": 822.427, "duration": 1.952}, {"text": "And it did, and it didn't.", "start": 825.593, "duration": 2.254}, {"text": "And it took about a year.", "start": 827.871, "duration": 2.063}, {"text": "And you know how there are people", "start": 829.958, "duration": 2.016}, {"text": "that, when they realize that vulnerability\nand tenderness are important,", "start": 831.998, "duration": 4.024}, {"text": "that they surrender and walk into it.", "start": 836.046, "duration": 2.031}, {"text": "A: that's not me,", "start": 839.231, "duration": 1.96}, {"text": "and B: I don't even hang out\nwith people like that.", "start": 841.215, "duration": 2.397}, {"text": "(Laughter)", "start": 843.636, "duration": 2.767}, {"text": "For me, it was a yearlong street fight.", "start": 846.427, "duration": 2.087}, {"text": "It was a slugfest.", "start": 849.752, "duration": 1.174}, {"text": "Vulnerability pushed, I pushed back.", "start": 851.339, "duration": 1.834}, {"text": "I lost the fight,", "start": 853.593, "duration": 3.087}, {"text": "but probably won my life back.", "start": 856.704, "duration": 1.699}, {"text": "And so then I went back into the research", "start": 858.727, "duration": 1.976}, {"text": "and spent the next couple of years", "start": 860.727, "duration": 1.676}, {"text": "really trying to understand\nwhat they, the whole-hearted,", "start": 862.427, "duration": 2.976}, {"text": "what choices they were making,\nand what we are doing with vulnerability.", "start": 865.427, "duration": 5.976}, {"text": "Why do we struggle with it so much?", "start": 871.427, "duration": 2.34}, {"text": "Am I alone in struggling\nwith vulnerability?", "start": 873.791, "duration": 2.161}, {"text": "No.", "start": 877.19, "duration": 1.213}, {"text": "So this is what I learned.", "start": 878.427, "duration": 1.461}, {"text": "We numb vulnerability --", "start": 881.959, "duration": 1.667}, {"text": "when we're waiting for the call.", "start": 884.68, "duration": 1.587}, {"text": "It was funny, I sent something out\non Twitter and on Facebook", "start": 886.291, "duration": 2.889}, {"text": "that says, \"How would you\ndefine vulnerability?", "start": 889.204, "duration": 2.274}, {"text": "What makes you feel vulnerable?\"", "start": 891.502, "duration": 1.548}, {"text": "And within an hour and a half,\nI had 150 responses.", "start": 893.074, "duration": 2.724}, {"text": "Because I wanted to know what's out there.", "start": 895.822, "duration": 2.973}, {"text": "Having to ask my husband for help\nbecause I'm sick, and we're newly married;", "start": 901.204, "duration": 5.023}, {"text": "initiating sex with my husband;", "start": 906.251, "duration": 2.007}, {"text": "initiating sex with my wife;", "start": 908.282, "duration": 2.714}, {"text": "being turned down; asking someone out;", "start": 911.02, "duration": 2.978}, {"text": "waiting for the doctor to call back;", "start": 914.022, "duration": 2.039}, {"text": "getting laid off; laying off people.", "start": 916.085, "duration": 2.342}, {"text": "This is the world we live in.", "start": 918.451, "duration": 1.404}, {"text": "We live in a vulnerable world.", "start": 920.962, "duration": 2.968}, {"text": "And one of the ways we deal\nwith it is we numb vulnerability.", "start": 923.954, "duration": 2.936}, {"text": "And I think there's evidence --", "start": 927.688, "duration": 1.715}, {"text": "and it's not the only reason\nthis evidence exists,", "start": 929.427, "duration": 2.381}, {"text": "but I think it's a huge cause --", "start": 931.832, "duration": 2.109}, {"text": "We are the most in-debt ...", "start": 933.965, "duration": 2.889}, {"text": "obese ...", "start": 938.538, "duration": 1.222}, {"text": "addicted and medicated\nadult cohort in U.S. history.", "start": 940.91, "duration": 4.159}, {"text": "The problem is -- and I learned this\nfrom the research --", "start": 948.315, "duration": 3.27}, {"text": "that you cannot selectively numb emotion.", "start": 951.609, "duration": 3.143}, {"text": "You can't say, here's the bad stuff.", "start": 955.291, "duration": 2.333}, {"text": "Here's vulnerability,\nhere's grief, here's shame,", "start": 958.427, "duration": 2.376}, {"text": "here's fear, here's disappointment.", "start": 960.827, "duration": 1.676}, {"text": "I don't want to feel these.", "start": 962.527, "duration": 1.876}, {"text": "I'm going to have a couple of beers\nand a banana nut muffin.", "start": 964.427, "duration": 2.882}, {"text": "(Laughter)", "start": 967.333, "duration": 2.686}, {"text": "I don't want to feel these.", "start": 970.043, "duration": 1.869}, {"text": "And I know that's knowing laughter.", "start": 971.936, "duration": 1.976}, {"text": "I hack into your lives for a living.", "start": 973.936, "duration": 2.467}, {"text": "God.", "start": 976.427, "duration": 1.976}, {"text": "(Laughter)", "start": 978.427, "duration": 2.547}, {"text": "You can't numb those hard feelings", "start": 980.998, "duration": 2.758}, {"text": "without numbing\nthe other affects, our emotions.", "start": 983.78, "duration": 2.634}, {"text": "You cannot selectively numb.", "start": 986.438, "duration": 1.452}, {"text": "So when we numb those,", "start": 987.914, "duration": 2.607}, {"text": "we numb joy,", "start": 990.545, "duration": 2.523}, {"text": "we numb gratitude,", "start": 993.092, "duration": 1.311}, {"text": "we numb happiness.", "start": 994.427, "duration": 1.3}, {"text": "And then, we are miserable,", "start": 997.148, "duration": 3.123}, {"text": "and we are looking\nfor purpose and meaning,", "start": 1000.295, "duration": 2.009}, {"text": "and then we feel vulnerable,", "start": 1002.328, "duration": 1.432}, {"text": "so then we have a couple of beers\nand a banana nut muffin.", "start": 1003.784, "duration": 2.808}, {"text": "And it becomes this dangerous cycle.", "start": 1006.616, "duration": 3.366}, {"text": "One of the things that I think\nwe need to think about", "start": 1011.087, "duration": 3.133}, {"text": "is why and how we numb.", "start": 1014.244, "duration": 1.976}, {"text": "And it doesn't just have to be addiction.", "start": 1016.928, "duration": 2.08}, {"text": "The other thing we do is we make\neverything that's uncertain certain.", "start": 1020.477, "duration": 3.373}, {"text": "Religion has gone from a belief\nin faith and mystery to certainty.", "start": 1025.427, "duration": 5.086}, {"text": "\"I'm right, you're wrong. Shut up.\"", "start": 1030.537, "duration": 1.682}, {"text": "That's it.", "start": 1034.187, "duration": 1.216}, {"text": "Just certain.", "start": 1036.611, "duration": 1.27}, {"text": "The more afraid we are,\nthe more vulnerable we are,", "start": 1038.34, "duration": 2.416}, {"text": "the more afraid we are.", "start": 1040.78, "duration": 1.385}, {"text": "This is what politics looks like today.", "start": 1042.189, "duration": 2.007}, {"text": "There's no discourse anymore.", "start": 1044.22, "duration": 1.675}, {"text": "There's no conversation.", "start": 1045.919, "duration": 1.484}, {"text": "There's just blame.", "start": 1047.807, "duration": 1.224}, {"text": "You know how blame\nis described in the research?", "start": 1049.055, "duration": 2.317}, {"text": "A way to discharge pain and discomfort.", "start": 1052.553, "duration": 2.499}, {"text": "We perfect.", "start": 1057.616, "duration": 1.19}, {"text": "If there's anyone who wants their life\nto look like this, it would be me,", "start": 1058.83, "duration": 3.778}, {"text": "but it doesn't work.", "start": 1062.632, "duration": 1.227}, {"text": "Because what we do is we take fat\nfrom our butts and put it in our cheeks.", "start": 1063.883, "duration": 3.62}, {"text": "(Laughter)", "start": 1067.527, "duration": 3.439}, {"text": "Which just, I hope in 100 years,\npeople will look back and go, \"Wow.\"", "start": 1070.99, "duration": 3.413}, {"text": "(Laughter)", "start": 1074.427, "duration": 2.523}, {"text": "And we perfect,\nmost dangerously, our children.", "start": 1076.974, "duration": 3.429}, {"text": "Let me tell you what we think\nabout children.", "start": 1080.427, "duration": 2.143}, {"text": "They're hardwired for struggle\nwhen they get here.", "start": 1082.594, "duration": 2.809}, {"text": "And when you hold those perfect\nlittle babies in your hand,", "start": 1085.427, "duration": 2.882}, {"text": "our job is not to say,\n\"Look at her, she's perfect.", "start": 1088.333, "duration": 2.958}, {"text": "My job is just to keep her perfect --", "start": 1091.315, "duration": 1.896}, {"text": "make sure she makes the tennis team\nby fifth grade and Yale by seventh.\"", "start": 1093.235, "duration": 3.407}, {"text": "That's not our job.", "start": 1096.666, "duration": 1.237}, {"text": "Our job is to look and say,", "start": 1097.927, "duration": 1.609}, {"text": "\"You know what? You're imperfect,\nand you're wired for struggle,", "start": 1099.56, "duration": 3.016}, {"text": "but you are worthy of love and belonging.\"", "start": 1102.6, "duration": 2.0}, {"text": "That's our job.", "start": 1105.501, "duration": 1.187}, {"text": "Show me a generation\nof kids raised like that,", "start": 1107.104, "duration": 2.23}, {"text": "and we'll end the problems,\nI think, that we see today.", "start": 1109.358, "duration": 2.601}, {"text": "We pretend that what we do\ndoesn't have an effect on people.", "start": 1111.983, "duration": 5.452}, {"text": "We do that in our personal lives.", "start": 1118.871, "duration": 1.634}, {"text": "We do that corporate --", "start": 1120.529, "duration": 1.223}, {"text": "whether it's a bailout, an oil spill ...", "start": 1121.776, "duration": 2.11}, {"text": "a recall.", "start": 1125.386, "duration": 1.16}, {"text": "We pretend like what we're doing", "start": 1126.57, "duration": 1.977}, {"text": "doesn't have a huge impact\non other people.", "start": 1128.571, "duration": 2.086}, {"text": "I would say to companies,\nthis is not our first rodeo, people.", "start": 1131.427, "duration": 3.274}, {"text": "We just need you to be authentic\nand real and say ...", "start": 1135.769, "duration": 2.667}, {"text": "\"We're sorry. We'll fix it.\"", "start": 1139.919, "duration": 2.144}, {"text": "But there's another way,\nand I'll leave you with this.", "start": 1145.535, "duration": 2.772}, {"text": "This is what I have found:", "start": 1148.331, "duration": 1.381}, {"text": "To let ourselves be seen,\ndeeply seen, vulnerably seen ...", "start": 1149.736, "duration": 4.523}, {"text": "to love with our whole hearts,\neven though there's no guarantee --", "start": 1156.891, "duration": 4.389}, {"text": "and that's really hard,", "start": 1161.304, "duration": 1.254}, {"text": "and I can tell you as a parent,\nthat's excruciatingly difficult --", "start": 1162.582, "duration": 3.341}, {"text": "to practice gratitude and joy\nin those moments of terror,", "start": 1168.495, "duration": 4.182}, {"text": "when we're wondering,\n\"Can I love you this much?", "start": 1172.701, "duration": 2.313}, {"text": "Can I believe in this this passionately?", "start": 1175.038, "duration": 2.186}, {"text": "Can I be this fierce about this?\"", "start": 1177.248, "duration": 1.93}, {"text": "just to be able to stop and, instead of\ncatastrophizing what might happen,", "start": 1179.202, "duration": 3.577}, {"text": "to say, \"I'm just so grateful,", "start": 1182.803, "duration": 1.977}, {"text": "because to feel this vulnerable\nmeans I'm alive.\"", "start": 1184.804, "duration": 2.4}, {"text": "And the last, which I think\nis probably the most important,", "start": 1188.748, "duration": 3.662}, {"text": "is to believe that we're enough.", "start": 1192.434, "duration": 1.65}, {"text": "Because when we work from a place,\nI believe, that says, \"I'm enough\" ...", "start": 1194.664, "duration": 3.849}, {"text": "then we stop screaming\nand start listening,", "start": 1200.743, "duration": 3.968}, {"text": "we're kinder and gentler\nto the people around us,", "start": 1204.735, "duration": 2.327}, {"text": "and we're kinder and gentler to ourselves.", "start": 1207.086, "duration": 2.149}, {"text": "That's all I have. Thank you.", "start": 1210.125, "duration": 1.478}, {"text": "(Applause)", "start": 1211.627, "duration": 2.593}]