[{"text": "Poor Toph, she must be so scared.", "start": 1.335, "duration": 2.961}, {"text": "You think you're so tough?", "start": 4.379, "duration": 1.293}, {"text": "Why don't you come up here\nso I can smack that grin off your face?", "start": 5.756, "duration": 3.086}, {"text": "I'm not smiling.", "start": 8.926, "duration": 1.751}, {"text": "I can't believe we gave up our tickets", "start": 10.761, "duration": 1.626}, {"text": "and now we're going through\nthe Serpent's Pass.", "start": 12.471, "duration": 1.877}, {"text": "I can't believe you're still complaining\nabout it.", "start": 14.431, "duration": 2.544}, {"text": "We can take 'em\nthree on three.", "start": 17.559, "duration": 2.586}, {"text": "Actually, Toph, there's four of us.", "start": 20.521, "duration": 1.543}, {"text": "Oh, I'm sorry. I didn't count you,\nyou know, no bending and all.", "start": 22.147, "duration": 4.129}, {"text": "I can still fight!", "start": 26.36, "duration": 1.543}, {"text": "Okay, three on three plus Sokka.", "start": 27.986, "duration": 2.545}, {"text": "Pathetic.", "start": 31.281, "duration": 1.46}, {"text": "Of all the avatars I've worked with,\nyou're by far the worst.", "start": 32.824, "duration": 4.255}, {"text": "I know that's only one other avatar,\nbut still.", "start": 37.329, "duration": 2.878}, {"text": "[screaming]", "start": 40.29, "duration": 0.793}, {"text": "The stars sure are beautiful tonight.", "start": 41.166, "duration": 2.419}, {"text": "Too bad you can't see them, Toph.", "start": 43.961, "duration": 1.918}, {"text": "[grunting]", "start": 45.963, "duration": 1.96}, {"text": "From now on,\nwe do whatever it takes to find Appa.", "start": 48.757, "duration": 2.294}, {"text": "Yeah, let's break some rules!", "start": 51.134, "duration": 2.67}, {"text": "What's this?", "start": 57.182, "duration": 1.126}, {"text": "I don't know.", "start": 59.059, "duration": 1.335}, {"text": "I mean, seriously, what's with you people?", "start": 60.561, "duration": 2.168}, {"text": "I'm blind!", "start": 62.813, "duration": 1.293}, {"text": "Sokka, the arrow was on Appa's head.", "start": 64.69, "duration": 2.21}, {"text": "This is his head!", "start": 67.609, "duration": 1.293}, {"text": "Why are feet coming out of it?", "start": 70.153, "duration": 1.877}, {"text": "Those are his horns.", "start": 72.155, "duration": 1.419}, {"text": "I haven't seen him in a while, okay?", "start": 73.991, "duration": 1.71}, {"text": "It looks just like 'em to me.", "start": 75.784, "duration": 2.086}, {"text": "Thank you. I worked really--", "start": 78.287, "duration": 1.835}, {"text": "Why do you feel the need to do that?", "start": 80.622, "duration": 1.794}, {"text": "Don't you see what she's doing?", "start": 82.499, "duration": 1.335}, {"text": "She's just playing with us.", "start": 83.917, "duration": 1.252}, {"text": "She's not even trying to win this fight.", "start": 85.252, "duration": 1.96}, {"text": "Not true. I'm giving it my all.", "start": 87.296, "duration": 2.46}, {"text": "You're trying to keep us here\nand waste all our time.", "start": 89.84, "duration": 2.669}, {"text": "Um, right. I think your friend\njust said that genius.", "start": 92.926, "duration": 3.17}, {"text": "And since you can't see, I should tell you\nI'm rolling my eyes.", "start": 96.263, "duration": 3.921}, {"text": "I'll roll your whole head!", "start": 100.267, "duration": 1.919}, {"text": "You were tossing me around\nlike a rag doll all day long.", "start": 102.269, "duration": 3.42}, {"text": "I know!\nAnd I'm an old lady.", "start": 105.772, "duration": 3.462}, {"text": "Imagine me in my prime,\nha, ha!", "start": 109.401, "duration": 3.086}, {"text": "I would have destroyed you!", "start": 112.654, "duration": 2.294}, {"text": "[laughing]", "start": 115.073, "duration": 0.835}, {"text": "Aang needs a firebending teacher.", "start": 115.991, "duration": 2.127}, {"text": "We can't think of a single person\nin the world to do the job.", "start": 118.202, "duration": 2.46}, {"text": "Now one shows up on a silver platter\nand you won't even think about it?", "start": 121.163, "duration": 3.962}, {"text": "I'm not having Zuko as my teacher.", "start": 127.878, "duration": 2.336}, {"text": "You're darn right you're not, buddy.", "start": 131.215, "duration": 1.71}, {"text": "Well, I guess that's settled.", "start": 133.133, "duration": 1.96}, {"text": "I'm beginning to wonder\nwho's really the blind one around here.", "start": 136.803, "duration": 2.878}, {"text": "There's a factory and re-education facility\nnot too far away.", "start": 140.098, "duration": 2.92}, {"text": "How do you know that?", "start": 143.101, "duration": 1.627}, {"text": "Bolin used to work for Kuvira.", "start": 144.895, "duration": 2.127}, {"text": "How did you end up dating\nthe kind of dipstick who works for Kuvira?", "start": 147.189, "duration": 4.338}, {"text": "Watch it, Toph!", "start": 158.367, "duration": 1.126}, {"text": "I am not Toph! I am Melon Lord!", "start": 159.576, "duration": 3.879}, {"text": "[laughing]", "start": 163.539, "duration": 1.668}, {"text": "Who are you?", "start": 165.29, "duration": 1.627}, {"text": "My name's Toph\nbecause it sounds like tough.", "start": 167.042, "duration": 3.128}, {"text": "And that's just what I am.", "start": 170.254, "duration": 1.668}, {"text": "Wait a minute,\nI sound like a guy,", "start": 172.047, "duration": 4.129}, {"text": "a really buff guy.", "start": 176.718, "duration": 2.002}, {"text": "Well, Toph,\nwhat you hear up there is the truth.", "start": 178.971, "duration": 2.419}, {"text": "It hurts, doesn't it?", "start": 181.557, "duration": 1.084}, {"text": "Are you kidding me?", "start": 182.808, "duration": 1.126}, {"text": "I wouldn't have cast it any other way.", "start": 184.101, "duration": 2.043}, {"text": "At least it's not a fly and bald lady.", "start": 187.187, "duration": 2.002}, {"text": "There it is!", "start": 191.942, "duration": 1.168}, {"text": "[trumpets sounding]", "start": 193.193, "duration": 1.085}, {"text": "That's what it will sound like\nwhen one of you spots it.", "start": 198.115, "duration": 2.377}, {"text": "The plan right now\nis to follow Appa's lead", "start": 202.494, "duration": 2.419}, {"text": "and get some sleep.", "start": 204.997, "duration": 1.251}, {"text": "Of course, we could have gotten\nsome sleep earlier", "start": 206.665, "duration": 2.044}, {"text": "if Toph didn't have such issues.", "start": 208.792, "duration": 2.336}, {"text": "What?", "start": 211.211, "duration": 1.043}, {"text": "We're trying to get there\nbefore my wife, Ying, has her baby.", "start": 212.337, "duration": 3.003}, {"text": "Great, we can travel\nthrough the Serpent's Pass together.", "start": 215.424, "duration": 2.794}, {"text": "The Serpent's Pass? Only the truly\ndesperate take that deadly route.", "start": 218.302, "duration": 5.005}, {"text": "Deadly route? Real pick Sokka.", "start": 223.39, "duration": 2.753}, {"text": "You're blind compared to me.", "start": 229.897, "duration": 2.168}, {"text": "Ah! Uh!", "start": 233.901, "duration": 0.959}, {"text": "Suki, are you okay?", "start": 241.658, "duration": 1.585}, {"text": "You have to be more careful.", "start": 243.452, "duration": 1.418}, {"text": "Come on.", "start": 245.078, "duration": 1.168}, {"text": "Thanks for saving my life, Toph.\nHey, no problem, Sokka.", "start": 246.872, "duration": 3.211}, {"text": "Everyone into the hole.", "start": 252.836, "duration": 1.919}, {"text": "It's so dark down here.", "start": 258.592, "duration": 1.335}, {"text": "I can't see a thing.", "start": 260.093, "duration": 1.502}, {"text": "- Oh, no! What a nightmare!\n- Sorry.", "start": 261.72, "duration": 2.669}, {"text": "So, how have you been, mother?", "start": 265.14, "duration": 1.835}, {"text": "I told you never to call me that.", "start": 267.059, "duration": 1.918}, {"text": "Aang, I found these nuts in your bag.", "start": 271.98, "duration": 2.294}, {"text": "I figured you wouldn't mind.", "start": 274.441, "duration": 1.668}, {"text": "And besides, even if you did,", "start": 276.318, "duration": 1.793}, {"text": "you're too much of a pushover\nto do anything about it.", "start": 278.278, "duration": 2.378}, {"text": "As a matter of fact, I don't mind.", "start": 281.281, "duration": 2.127}, {"text": "I'm happy to share anything I have.", "start": 283.575, "duration": 1.585}, {"text": "You know, I'm really glad\nyou feel that way", "start": 285.661, "duration": 2.335}, {"text": "because I also have\nthis great new nutcracker.", "start": 288.163, "duration": 3.045}, {"text": "Actually, I'd prefer if you didn't--", "start": 294.92, "duration": 1.501}, {"text": "That's an antique,\nhandcrafted by the Monks.", "start": 297.297, "duration": 2.211}, {"text": "It's a delicate instrument.", "start": 300.175, "duration": 1.543}, {"text": "It's not the only delicate instrument\naround here.", "start": 301.802, "duration": 2.794}, {"text": "So, basically you're saying that", "start": 308.684, "duration": 2.043}, {"text": "everything I've ever accomplished\nhas been pointless?", "start": 310.894, "duration": 2.962}, {"text": "And I thought Beifong was grumpy.", "start": 314.189, "duration": 1.585}, {"text": "I'm the original Beifong!", "start": 315.858, "duration": 2.627}, {"text": "Get ready to push.", "start": 318.569, "duration": 1.334}, {"text": "One, two, three. Push!", "start": 320.445, "duration": 4.255}, {"text": "[screaming]", "start": 324.783, "duration": 1.835}, {"text": "[baby crying]", "start": 327.16, "duration": 1.46}, {"text": "It's a girl!", "start": 328.745, "duration": 1.127}, {"text": "So, you want to go see the baby?", "start": 330.455, "duration": 2.002}, {"text": "Or are you going to faint\nlike an old lady again?", "start": 332.624, "duration": 2.378}, {"text": "I assure you the fire nation\ncannot penetrate this wall.", "start": 335.085, "duration": 4.046}, {"text": "Many have tried to break through it\nbut none have succeeded.", "start": 339.798, "duration": 4.171}, {"text": "What about the Dragon of the West?\nHe got in.", "start": 344.72, "duration": 2.752}, {"text": "Well, technically, yes.", "start": 347.723, "duration": 2.586}, {"text": "I think she looks cute,", "start": 350.392, "duration": 1.835}, {"text": "like that time we put a sweater\non your pet poodle monkey.", "start": 352.311, "duration": 2.627}, {"text": "[laughing]", "start": 355.063, "duration": 2.628}, {"text": "Good one, Star.", "start": 358.483, "duration": 1.377}, {"text": "Let's go, Toph.", "start": 360.277, "duration": 1.46}, {"text": "No, no, that was a good one.", "start": 361.862, "duration": 2.544}, {"text": "Like your poodle monkey.", "start": 364.573, "duration": 1.46}, {"text": "[laughing]", "start": 366.116, "duration": 1.627}, {"text": "You know what else is a good one?", "start": 367.826, "duration": 1.543}, {"text": "[screaming]", "start": 370.913, "duration": 1.042}, {"text": "Sokka, Long Feng is in control\nof the city.", "start": 373.123, "duration": 2.461}, {"text": "His conspiracy with the Dai Li\nis too powerful.", "start": 375.667, "duration": 2.628}, {"text": "I think we should just keep flying\nand leave this horrible place behind us.", "start": 378.545, "duration": 3.295}, {"text": "I'm with Sweetness.", "start": 381.924, "duration": 1.418}, {"text": "I've seen enough of Ba Sing Se,\nand I can't even see.", "start": 383.509, "duration": 4.129}, {"text": "The king is having a party\nat the palace tonight for his pet bear.", "start": 387.721, "duration": 3.045}, {"text": "You mean platypus bear?", "start": 391.141, "duration": 1.627}, {"text": "No, it just says bear.", "start": 392.976, "duration": 2.169}, {"text": "Certainly, you mean his pet skunk bear.", "start": 395.229, "duration": 2.294}, {"text": "Or his armadillo bear?", "start": 397.606, "duration": 1.293}, {"text": "Gopher bear?", "start": 398.982, "duration": 1.126}, {"text": "Just bear.", "start": 400.526, "duration": 1.626}, {"text": "This place is weird.", "start": 403.278, "duration": 1.919}, {"text": "[music]", "start": 405.28, "duration": 3.087}, {"text": "[laughing]", "start": 408.867, "duration": 1.502}, {"text": "Wow, you look beautiful.", "start": 410.452, "duration": 1.919}, {"text": "Don't talk to the commoners, Katara,", "start": 414.039, "duration": 1.835}, {"text": "first rule of society.", "start": 416.124, "duration": 1.335}, {"text": "Another crab puff, please.", "start": 417.543, "duration": 1.835}, {"text": "You found us.", "start": 420.128, "duration": 1.168}, {"text": "I know your little footsteps anywhere,\nTwinkle Toes.", "start": 421.547, "duration": 2.711}, {"text": "Ah! Toph, aren't you going to get ready\nfor the day?", "start": 426.802, "duration": 2.836}, {"text": "I'm ready.", "start": 436.687, "duration": 0.917}, {"text": "[music playing]", "start": 437.688, "duration": 2.21}, {"text": "[screaming]", "start": 455.706, "duration": 1.835}, {"text": "Why won't you trust me?", "start": 457.624, "duration": 1.293}, {"text": "Gee, I wonder.", "start": 461.044, "duration": 1.335}, {"text": "Was this guy your boyfriend\nor something?", "start": 462.838, "duration": 2.753}, {"text": "What? No!", "start": 465.674, "duration": 1.585}, {"text": "I can tell you're lying.", "start": 467.843, "duration": 2.294}, {"text": "We're finally leaving Ba Sing Se,\nworst city ever!", "start": 470.971, "duration": 5.088}, {"text": "Good job, Twinkle Toes,\nvisualize then attack.", "start": 480.439, "duration": 3.253}, {"text": "Uh! Ah!", "start": 485.36, "duration": 1.544}, {"text": "Maybe you should take your own advice,\nToph.", "start": 487.279, "duration": 2.21}, {"text": "What's the matter?\nCan't handle some dirt,", "start": 490.032, "duration": 2.043}, {"text": "Madame Fussy Britches?", "start": 492.159, "duration": 2.002}, {"text": "You need me\nand I will never turn my back on you.", "start": 494.786, "duration": 3.421}, {"text": "Sokka, you really do have a heart.", "start": 498.79, "duration": 2.545}, {"text": "Really does have a heart, doesn't he?", "start": 503.42, "duration": 1.627}, {"text": "Uh!", "start": 506.548, "duration": 1.085}, {"text": "Toph got us money.", "start": 507.716, "duration": 0.959}, {"text": "He scammed one of those guys in town", "start": 509.468, "duration": 1.626}, {"text": "who moves the shells around\nall sneaky like.", "start": 511.178, "duration": 2.002}, {"text": "She used earthbending\nto win the game, classic!", "start": 514.097, "duration": 3.295}, {"text": "Ah, so she cheated?", "start": 517.476, "duration": 1.835}, {"text": "Hey, I only cheated\nbecause he was cheating.", "start": 519.394, "duration": 2.628}, {"text": "I cheated a cheater.", "start": 522.231, "duration": 1.334}, {"text": "What's wrong with that?", "start": 523.899, "duration": 1.126}, {"text": "I'm just saying, this isn't something\nwe should make a habit of doing.", "start": 525.108, "duration": 3.087}, {"text": "Why, because it's fun and you hate fun?", "start": 528.278, "duration": 3.42}, {"text": "[music playing]", "start": 531.782, "duration": 1.501}, {"text": "The Boulder feels conflicted\nabout fighting a young, blind girl.", "start": 553.47, "duration": 5.13}, {"text": "Sounds to me like you're scared, Boulder.", "start": 558.934, "duration": 3.045}, {"text": "The Boulder's over his conflicted feelings", "start": 563.48, "duration": 2.753}, {"text": "and now he's ready to bury you\nin a rock-a-lanche.", "start": 566.316, "duration": 3.671}, {"text": "Whenever you're ready, The Pebble.", "start": 570.07, "duration": 2.669}, {"text": "[laughing]", "start": 572.823, "duration": 2.169}, {"text": "Did I mention that\nI'm an incurable prankster?", "start": 575.075, "duration": 3.42}, {"text": "I don't do that!", "start": 579.913, "duration": 1.335}, {"text": "That's not what I'm like!", "start": 581.373, "duration": 1.376}, {"text": "And I'm not a woman!", "start": 582.958, "duration": 1.627}, {"text": "[laughing]", "start": 584.793, "duration": 1.627}, {"text": "Oh, they nailed you, Twinkle Toes.", "start": 586.503, "duration": 2.294}, {"text": "[laughing]", "start": 588.881, "duration": 1.668}, {"text": "I have a surprise for everyone!", "start": 590.632, "duration": 1.919}, {"text": "I knew it!\nYou did have a secret thing with Haru!", "start": 592.968, "duration": 3.045}, {"text": "Well, look at you, Buster.", "start": 597.931, "duration": 2.211}, {"text": "Now that your firebending's gone,", "start": 600.267, "duration": 1.251}, {"text": "I guess we should call you\nThe Loser Lord.", "start": 601.602, "duration": 3.003}, {"text": "I am The Phoenix King.\nUh, uh.", "start": 604.688, "duration": 5.339}, {"text": "Oh, sorry. Didn't mean to offend you\nPhoenix King of Getting His Butt Whooped.", "start": 610.11, "duration": 4.713}, {"text": "Yeah! Or how about\nKing of the Guys Who Don't Win?", "start": 614.907, "duration": 5.463}, {"text": "Leave the nicknames to us, honey.", "start": 620.913, "duration": 1.626}, {"text": "It's another one of her tricks.", "start": 628.17, "duration": 1.71}, {"text": "There's a giant hole in the box.", "start": 630.214, "duration": 1.835}, {"text": "How is that a trick?", "start": 632.216, "duration": 1.126}, {"text": "It's not.", "start": 633.509, "duration": 1.001}, {"text": "It's the real deal.", "start": 635.135, "duration": 1.502}, {"text": "Ah!", "start": 641.099, "duration": 0.876}, {"text": "[dramatic music]", "start": 644.061, "duration": 1.918}, {"text": "I am the greatest Earthbender\nin the world!", "start": 646.063, "duration": 2.544}, {"text": "Don't you two dunderheads ever forget it!", "start": 648.774, "duration": 2.21}]