[{"text": "Meet Arnold,today he'll go to the amazon", "start": 0.025, "duration": 3.28}, {"text": "To get claiming with the local inhabitans!", "start": 3.305, "duration": 1.79}, {"text": "Which ones?", "start": 5.825, "duration": 1.23}, {"text": "Piranhas! There", "start": 7.995, "duration": 1.0}, {"text": "are about 50 different kinds of Piranhas,of which", "start": 8.995, "duration": 3.03}, {"text": "Only a few eat the flesh of living banics", "start": 12.025, "duration": 2.73}, {"text": "All other species are either vegetarians", "start": 14.755, "duration": 2.88}, {"text": "Or eat only", "start": 17.635, "duration": 3.06}, {"text": " ", "start": 20.695, "duration": 3.29}, {"text": " ", "start": 24.065, "duration": 2.1}, {"text": " ", "start": 26.495, "duration": 2.96}, {"text": " ", "start": 29.725, "duration": 3.08}, {"text": " ", "start": 32.805, "duration": 3.38}, {"text": " ", "start": 36.355, "duration": 1.91}, {"text": " ", "start": 39.195, "duration": 1.0}, {"text": " ", "start": 41.205, "duration": 3.26}, {"text": " ", "start": 44.625, "duration": 2.89}, {"text": " ", "start": 47.655, "duration": 3.19}, {"text": " ", "start": 50.845, "duration": 1.24}, {"text": " ", "start": 52.425, "duration": 2.79}, {"text": " ", "start": 55.915, "duration": 1.0}, {"text": " ", "start": 57.015, "duration": 3.08}, {"text": " ", "start": 60.095, "duration": 3.24}, {"text": " ", "start": 63.645, "duration": 2.42}, {"text": " ", "start": 67.845, "duration": 3.25}, {"text": " ", "start": 71.095, "duration": 3.02}, {"text": " ", "start": 74.125, "duration": 2.87}, {"text": " ", "start": 76.995, "duration": 3.03}, {"text": " ", "start": 80.025, "duration": 1.99}, {"text": " ", "start": 82.335, "duration": 1.28}, {"text": " ", "start": 83.955, "duration": 3.13}, {"text": " ", "start": 87.085, "duration": 3.05}, {"text": " ", "start": 90.135, "duration": 2.86}, {"text": " ", "start": 92.995, "duration": 3.02}, {"text": " ", "start": 96.015, "duration": 3.06}, {"text": " ", "start": 99.075, "duration": 3.2}, {"text": " ", "start": 102.275, "duration": 3.07}, {"text": " ", "start": 105.345, "duration": 2.77}, {"text": " ", "start": 108.115, "duration": 2.94}, {"text": " ", "start": 111.095, "duration": 3.0}, {"text": " ", "start": 114.095, "duration": 2.98}, {"text": " ", "start": 117.075, "duration": 3.41}, {"text": " ", "start": 120.485, "duration": 1.94}, {"text": " ", "start": 122.745, "duration": 3.5}, {"text": " ", "start": 126.265, "duration": 2.81}, {"text": " ", "start": 129.075, "duration": 2.67}, {"text": " ", "start": 131.975, "duration": 2.67}, {"text": " ", "start": 134.645, "duration": 1.89}, {"text": "The sponsor of this episode is NordVPN!", "start": 138.175, "duration": 3.16}, {"text": " ", "start": 141.765, "duration": 1.0}, {"text": " ", "start": 142.845, "duration": 2.51}, {"text": " ", "start": 145.895, "duration": 2.67}, {"text": " ", "start": 149.015, "duration": 3.34}, {"text": " ", "start": 152.585, "duration": 1.62}, {"text": " ", "start": 154.515, "duration": 2.78}, {"text": " ", "start": 157.295, "duration": 2.84}, {"text": " ", "start": 160.135, "duration": 2.82}, {"text": " ", "start": 162.955, "duration": 3.17}, {"text": " ", "start": 166.125, "duration": 2.56}, {"text": " ", "start": 168.915, "duration": 2.88}, {"text": " ", "start": 171.795, "duration": 3.07}, {"text": " ", "start": 174.865, "duration": 3.35}, {"text": " ", "start": 178.215, "duration": 3.13}, {"text": " ", "start": 181.345, "duration": 2.94}, {"text": " ", "start": 184.285, "duration": 2.97}, {"text": " ", "start": 187.255, "duration": 3.22}, {"text": " ", "start": 190.475, "duration": 1.0}, {"text": " ", "start": 191.615, "duration": 2.53}, {"text": " ", "start": 195.395, "duration": 3.04}, {"text": " ", "start": 198.505, "duration": 1.67}, {"text": " ", "start": 200.515, "duration": 1.97}, {"text": " ", "start": 202.865, "duration": 1.0}, {"text": " ", "start": 204.145, "duration": 1.0}]