[{"text": "The Matrix is a system, Neo.", "start": 6.463, "duration": 1.542}, {"text": "That system is our enemy.", "start": 9.758, "duration": 1.292}, {"text": "But when you're inside,\nwhat do you see?", "start": 11.677, "duration": 2.334}, {"text": "Businessmen, teachers,\nlawyers, carpenters.", "start": 14.263, "duration": 3.794}, {"text": "The very minds of the people\nwe are trying to save.", "start": 18.517, "duration": 2.585}, {"text": "But until we do, these people are\na part of that system...", "start": 21.353, "duration": 2.96}, {"text": "...and that makes them our enemy.", "start": 24.565, "duration": 1.917}, {"text": "You have to understand...", "start": 26.65, "duration": 1.209}, {"text": "...most of these people are not\nready to be unplugged.", "start": 28.11, "duration": 3.336}, {"text": "And many of them are so inert...", "start": 31.697, "duration": 1.584}, {"text": "...so hopelessly dependent\non the system...", "start": 33.532, "duration": 2.418}, {"text": "...that they will fight to protect it.", "start": 36.201, "duration": 2.71}, {"text": "Were you listening to me or looking\nat the woman in the red dress?", "start": 40.414, "duration": 3.753}, {"text": "- I was--\n- Look again.", "start": 44.334, "duration": 1.751}, {"text": "Freeze it.", "start": 47.337, "duration": 1.084}, {"text": "- This isn't the Matrix?\n- No.", "start": 55.053, "duration": 1.626}, {"text": "It's another training program\ndesigned to teach you one thing:", "start": 58.474, "duration": 3.836}, {"text": "If you are not one of us,\nyou are one of them.", "start": 62.936, "duration": 2.418}, {"text": "- What are they?\n- Sentient programs.", "start": 65.898, "duration": 2.793}, {"text": "They can move in and out of any\nsoftware still hardwired to their system.", "start": 69.443, "duration": 4.295}, {"text": "That means that anyone\nwe haven't unplugged...", "start": 74.114, "duration": 3.378}, {"text": "...is potentially an agent.", "start": 77.826, "duration": 1.334}, {"text": "Inside the Matrix...", "start": 80.12, "duration": 1.834}, {"text": "...they are everyone...", "start": 82.539, "duration": 1.709}, {"text": "...and they are no one.", "start": 84.583, "duration": 1.709}, {"text": "We have survived by hiding\nand running from them...", "start": 86.543, "duration": 3.127}, {"text": "...but they are the gatekeepers.", "start": 89.922, "duration": 1.625}, {"text": "They're guarding all the doors\nand holding all the keys.", "start": 91.799, "duration": 2.96}, {"text": "Sooner or later, someone will\nhave to fight them.", "start": 95.01, "duration": 2.835}, {"text": "Someone?", "start": 98.013, "duration": 1.209}, {"text": "I won't lie to you, Neo.", "start": 99.556, "duration": 1.417}, {"text": "Every single man or woman who\nhas fought an agent, has died.", "start": 101.433, "duration": 4.837}, {"text": "But where they have failed,\nyou will succeed.", "start": 106.522, "duration": 2.376}, {"text": "Why?", "start": 109.066, "duration": 1.083}, {"text": "I've seen an agent punch\nthrough a concrete wall.", "start": 110.4, "duration": 2.293}, {"text": "Men have emptied entire clips at them\nand hit nothing but air.", "start": 112.945, "duration": 3.586}, {"text": "Yet their strength and speed are still\nbased in a world built on rules.", "start": 116.782, "duration": 4.628}, {"text": "Because of that...", "start": 121.662, "duration": 1.125}, {"text": "...they will never be as strong\nor as fast as you can be.", "start": 123.038, "duration": 3.377}, {"text": "What are you telling me?", "start": 130.712, "duration": 1.876}, {"text": "That I can dodge bullets?", "start": 133.298, "duration": 1.459}, {"text": "No, Neo.", "start": 136.76, "duration": 1.375}, {"text": "I'm trying to tell you\nthat when you're ready...", "start": 138.637, "duration": 2.919}, {"text": "...you won't have to.", "start": 142.432, "duration": 1.334}, {"text": "We got trouble.", "start": 147.896, "duration": 1.209}, {"text": "- Did Zion send the warning?\n- No, another ship.", "start": 168.041, "duration": 2.46}, {"text": "Shit.", "start": 173.755, "duration": 1.292}, {"text": "- Squiddy's sweeping in quick.\n- Squiddy?", "start": 175.299, "duration": 2.876}, {"text": "A sentinel. A killing machine\ndesigned for one thing.", "start": 178.385, "duration": 3.211}, {"text": "Search and destroy.", "start": 181.847, "duration": 1.208}, {"text": "Set her down there.", "start": 184.391, "duration": 1.167}, {"text": "How are we doing, Tank?", "start": 206.83, "duration": 1.501}, {"text": "Power off-line.", "start": 217.049, "duration": 1.166}, {"text": "EMP armed...", "start": 218.717, "duration": 1.959}, {"text": "- ...and ready.\n- EMP?", "start": 221.219, "duration": 1.543}, {"text": "Electromagnetic pulse.", "start": 223.055, "duration": 1.876}, {"text": "Disables any electrical system\nin the blast radius.", "start": 225.182, "duration": 2.877}, {"text": "It's the only weapon we have\nagainst the machines.", "start": 228.226, "duration": 2.293}, {"text": "- Where are we?\n- Their old service and waste systems.", "start": 236.318, "duration": 3.127}, {"text": "Sewers.", "start": 240.697, "duration": 1.125}, {"text": "There used to be cities\nthat spanned hundreds of miles.", "start": 242.032, "duration": 2.71}, {"text": "Now these sewers are\nall that's left.", "start": 245.243, "duration": 1.918}, {"text": "Quiet.", "start": 247.412, "duration": 1.334}]